demo_example_pkg/__init__.py
demo_example_pkg/hello.py
Demo_example_pkg-0.0.3.dist-info/LICENSE
Demo_example_pkg-0.0.3.dist-info/METADATA
Demo_example_pkg-0.0.3.dist-info/WHEEL
Demo_example_pkg-0.0.3.dist-info/top_level.txt
Demo_example_pkg-0.0.3.dist-info/RECORD
