Metadata-Version: 2.1
Name: Demo-example-pkg
Version: 0.0.3
Summary: A small example package
Home-page: https://github.com/gituser/example-pkg
Author: Aakash Aggarwal
Author-email: aakash10975@gmail.com
License: GPT
Platform: UNKNOWN
Classifier: Programming Language :: Python :: 2
Classifier: Operating System :: OS Independent
Requires-Python: >=2.7.16
Requires-Dist: pyspark (>=2.0)
